.bzrignore
CHANGES.txt
LICENSE.GPL
LICENSE.txt
README.txt
bootstrap.py
buildout.cfg
setup.py
src/mailman/__init__.py
src/mailman/Bouncers/BouncerAPI.py
src/mailman/Bouncers/Caiwireless.py
src/mailman/Bouncers/Compuserve.py
src/mailman/Bouncers/DSN.py
src/mailman/Bouncers/Exchange.py
src/mailman/Bouncers/Exim.py
src/mailman/Bouncers/GroupWise.py
src/mailman/Bouncers/LLNL.py
src/mailman/Bouncers/Microsoft.py
src/mailman/Bouncers/Netscape.py
src/mailman/Bouncers/Postfix.py
src/mailman/Bouncers/Qmail.py
src/mailman/Bouncers/SMTP32.py
src/mailman/Bouncers/SimpleMatch.py
src/mailman/Bouncers/SimpleWarning.py
src/mailman/Bouncers/Sina.py
src/mailman/Bouncers/Yahoo.py
src/mailman/Bouncers/Yale.py
src/mailman/Bouncers/__init__.py
src/zw/__init__.py
src/zw.mail.incoming.egg-info/PKG-INFO
src/zw.mail.incoming.egg-info/SOURCES.txt
src/zw.mail.incoming.egg-info/dependency_links.txt
src/zw.mail.incoming.egg-info/entry_points.txt
src/zw.mail.incoming.egg-info/namespace_packages.txt
src/zw.mail.incoming.egg-info/not-zip-safe
src/zw.mail.incoming.egg-info/requires.txt
src/zw.mail.incoming.egg-info/top_level.txt
src/zw/mail/__init__.py
src/zw/mail/incoming/README.txt
src/zw/mail/incoming/__init__.py
src/zw/mail/incoming/configure.zcml
src/zw/mail/incoming/events.py
src/zw/mail/incoming/inbox.py
src/zw/mail/incoming/interfaces.py
src/zw/mail/incoming/meta.zcml
src/zw/mail/incoming/processor.py
src/zw/mail/incoming/script.py
src/zw/mail/incoming/tests.py
src/zw/mail/incoming/vocabulary.py
src/zw/mail/incoming/zcml.py
src/zw/mail/incoming/zw.mail.incoming-configure.zcml
src/zw/mail/incoming/zw.mail.incoming-meta.zcml